{
  "_meta.version": "1.0",
  "_meta.note": "Русский перевод (machine-translated, contributions welcome).",

  "panel.title": "Wrath Tactics",
  "tab.global": "Общие",
  "tab.presets": "Шаблоны",
  "toggle.global_rules": "Общие правила",
  "toggle.tactics.enabled": "Тактики включены для {0}",
  "toggle.tactics.disabled": "Тактики выключены для {0}",

  "button.new_rule": "+ Новое правило",
  "button.from_preset": "+ Из шаблона",
  "button.add_condition": "+ Условие",
  "button.add_or_group": "+ ИЛИ (новая группа)",
  "button.add_fallback": "+ Запасное",
  "button.on": "ВКЛ",
  "button.off": "ВЫКЛ",
  "button.copy": "Копировать",
  "button.export": "Экспорт",
  "button.promote_to_preset": "↥ Шаблон",
  "button.unlink_edit": "Отвязать и редактировать",

  "filter.rules.placeholder": "Фильтр правил…",
  "filter.no_matching_rules": "Нет подходящих правил",
  "filter.no_matching_presets": "Нет подходящих шаблонов",

  "section.if": "ЕСЛИ:",
  "section.then": "ТО:",
  "section.target": "ЦЕЛЬ:",
  "section.or_separator": "-- ИЛИ --",

  "linked.name_format": "🔗 {0}",
  "linked.badge": "Привязано к шаблону: {0}",
  "linked.summary": "ЕСЛИ: {0} | ТО: {1}{2} | Цель: {3}",
  "linked.summary.condition_count": "{0} условий",

  "source.all": "Все источники",
  "source.spell_only": "Только заклинание",
  "source.scroll_only": "Только свиток",
  "source.potion_only": "Только зелье",
  "source.spell_scroll": "Заклинание + Свиток",
  "source.spell_potion": "Заклинание + Зелье",
  "source.scroll_potion": "Свиток + Зелье",

  "placeholder.none_available": "(нет доступных)",
  "placeholder.pick_buff": "(выберите бафф)",

  "target.filter.condition": "Состояние:",
  "target.filter.buff_guid": "GUID баффа:",
  "target.filter.creature_type": "Тип существа:",

  "cooldown.label": "Перезарядка (раунды):",

  "default.new_rule_name": "Новое правило",
  "clone.suffix": " (копия)",

  "preset.hint": "Шаблоны — повторно используемые правила. Прикрепите их на любой вкладке персонажа через \"+ Из шаблона\". Изменения здесь распространяются на все связанные копии.",
  "preset.empty": "Шаблонов пока нет.",
  "preset.default_name": "Новый шаблон",
  "preset.imported_default_name": "Импортированный шаблон",
  "preset.imported_suffix": " (импортирован)",
  "preset.imported_suffix_n": " (импортирован {0})",
  "preset.button.export_all": "Экспортировать все шаблоны в буфер",
  "preset.button.import": "Импортировать шаблоны из буфера",
  "preset.button.new": "+ Новый шаблон",
  "preset.button.open_folder": "Открыть папку шаблонов",

  "button.close": "Закрыть",
  "button.edit": "Изменить",
  "button.delete": "Удалить",

  "status.save_failed": "Ошибка сохранения — см. лог мода: {0}",
  "status.context.new_preset": "новый шаблон",
  "status.context.rename": "переименование",
  "status.context.delete": "удаление",
  "status.context.edit": "правка",
  "status.export_copied": "Скопировано {0} шаблон(ов) в буфер.",
  "status.clipboard_empty": "Буфер пуст. Сначала скопируйте JSON-массив шаблонов.",
  "status.clipboard_invalid_json": "Некорректный JSON в буфере: {0}",
  "status.clipboard_not_array": "Буфер не содержит JSON-массив шаблонов.",
  "status.import_partial_failure": "Импортировано {0} шаблон(ов), {1} с ошибкой — см. лог мода.",
  "status.import_with_renames": "Импортировано {0} шаблон(ов) — {1} переименовано из-за конфликтов.",
  "status.import_success": "Импортировано {0} шаблон(ов).",

  "picker.no_abilities": "(нет доступных способностей)",
  "picker.no_matches": "Нет совпадений для \"{0}\"",
  "picker.no_suggestions": "(нет предложений — введите для поиска)",
  "picker.section.recents": "★ Недавние",
  "picker.section.common_enemy": "Частые баффы врагов",
  "picker.section.common_ally": "Частые баффы союзников",
  "picker.capped": "(показано {0} совпадений — уточните поиск)",

  "item.prefix.scroll": "(Свиток)",
  "item.prefix.potion": "(Зелье)",
  "item.prefix.wand": "(Жезл)",
  "item.prefix.item": "(Предмет)",

  "preset.default.emergency_self_heal": "Экстренное самолечение",
  "preset.default.party_channel_heal": "Лечение группы (Канал позитива)",
  "preset.default.counter_swarms": "Против роев (метательное)",
  "preset.default.coup_de_grace": "Добивание беспомощных",
  "preset.default.channel_vs_undead": "Канал против нежити",
  "preset.default.smite_evil": "Кара зла",

  "condition.with": "с",
  "bool.yes": "Да",
  "bool.no": "Нет",

  "enum.subject.Self": "Себя",
  "enum.subject.Ally": "Союзник",
  "enum.subject.AllyCount": "Кол-во союзников",
  "enum.subject.Enemy": "Враг",
  "enum.subject.EnemyCount": "Кол-во врагов",
  "enum.subject.Combat": "Бой",
  "enum.subject.EnemyBiggestThreat": "Враг: макс. угроза",
  "enum.subject.EnemyLowestThreat": "Враг: мин. угроза",
  "enum.subject.EnemyHighestHp": "Враг: макс. HP%",
  "enum.subject.EnemyLowestHp": "Враг: мин. HP%",
  "enum.subject.EnemyLowestAC": "Враг: мин. КБ",
  "enum.subject.EnemyHighestAC": "Враг: макс. КБ",
  "enum.subject.EnemyLowestFort": "Враг: мин. Стой",
  "enum.subject.EnemyHighestFort": "Враг: макс. Стой",
  "enum.subject.EnemyLowestReflex": "Враг: мин. Реак",
  "enum.subject.EnemyHighestReflex": "Враг: макс. Реак",
  "enum.subject.EnemyLowestWill": "Враг: мин. Воля",
  "enum.subject.EnemyHighestWill": "Враг: макс. Воля",
  "enum.subject.EnemyHighestHD": "Враг: макс. КЗ",
  "enum.subject.EnemyLowestHD": "Враг: мин. КЗ",

  "enum.property.HpPercent": "HP%",
  "enum.property.AC": "КБ",
  "enum.property.HasBuff": "Есть бафф",
  "enum.property.HasCondition": "Есть состояние",
  "enum.property.SpellSlotsAtLevel": "Слоты на уровне",
  "enum.property.SpellSlotsAboveLevel": "Слоты выше уровня",
  "enum.property.Resource": "Ресурс",
  "enum.property.CreatureType": "Тип существа",
  "enum.property.CombatRounds": "Раунды боя",
  "enum.property.IsDead": "Мёртв",
  "enum.property.SaveFortitude": "Спасбросок Стойкости",
  "enum.property.SaveReflex": "Спасбросок Реакции",
  "enum.property.SaveWill": "Спасбросок Воли",
  "enum.property.Alignment": "Мировоззрение",
  "enum.property.IsInCombat": "В бою",
  "enum.property.HitDice": "Кости здоровья",
  "enum.property.SpellDCMinusSave": "СЛ − Спасбросок",
  "enum.property.HasClass": "Есть класс",
  "enum.property.WithinRange": "В радиусе",
  "enum.property.ABMinusAC": "БА − КБ",
  "enum.property.IsTargetingSelf": "Цель — я",
  "enum.property.IsTargetingAlly": "Цель — союзник",
  "enum.property.IsTargetedByAlly": "Цель союзника",
  "enum.property.IsTargetedByEnemy": "Цель врага",
  "enum.property.IsSummon": "Призванное существо",
  "enum.property.EnemyHDMinusPartyLevel": "КЗ − Группа",

  "enum.action.CastSpell": "Заклинание",
  "enum.action.CastAbility": "Способность",
  "enum.action.UseItem": "Предмет",
  "enum.action.ToggleActivatable": "Переключить",
  "enum.action.AttackTarget": "Атаковать",
  "enum.action.Heal": "Лечить",
  "enum.action.DoNothing": "Бездействовать",
  "enum.action.ThrowSplash": "Метнуть",

  "enum.target.Self": "Себя",
  "enum.target.AllyLowestHp": "Союзник: мин. HP",
  "enum.target.AllyWithCondition": "Союзник со статусом",
  "enum.target.AllyMissingBuff": "Союзник без баффа",
  "enum.target.EnemyNearest": "Враг: ближайший",
  "enum.target.EnemyLowestHp": "Враг: мин. HP",
  "enum.target.EnemyHighestHp": "Враг: макс. HP",
  "enum.target.EnemyHighestAC": "Враг: макс. КБ",
  "enum.target.EnemyLowestAC": "Враг: мин. КБ",
  "enum.target.EnemyHighestFort": "Враг: макс. Стой",
  "enum.target.EnemyLowestFort": "Враг: мин. Стой",
  "enum.target.EnemyHighestReflex": "Враг: макс. Реак",
  "enum.target.EnemyLowestReflex": "Враг: мин. Реак",
  "enum.target.EnemyHighestWill": "Враг: макс. Воля",
  "enum.target.EnemyLowestWill": "Враг: мин. Воля",
  "enum.target.EnemyHighestThreat": "Враг: макс. угроза",
  "enum.target.EnemyCreatureType": "Враг: тип",
  "enum.target.ConditionTarget": "Цель условия",
  "enum.target.EnemyHighestHD": "Враг: макс. КЗ",
  "enum.target.EnemyLowestHD": "Враг: мин. КЗ",
  "enum.target.PointAtSelf": "Точка перед собой",
  "enum.target.PointAtConditionTarget": "Точка у цели условия",

  "enum.heal_mode.Any": "Любой",
  "enum.heal_mode.Strongest": "Сильнейший",
  "enum.heal_mode.Weakest": "Слабейший",

  "enum.heal_energy.Auto": "Авто",
  "enum.heal_energy.Positive": "Позитивная",
  "enum.heal_energy.Negative": "Негативная",
  "enum.heal_energy.None": "Нет",

  "enum.toggle_mode.On": "Вкл",
  "enum.toggle_mode.Off": "Выкл",

  "enum.splash_mode.Any": "Любой",
  "enum.splash_mode.Strongest": "Сильнейший",
  "enum.splash_mode.Cheapest": "Дешёвый",

  "enum.range.Melee": "Ближний (≤2 м)",
  "enum.range.Cone": "Конус (≤5 м)",
  "enum.range.Short": "Короткий (≤10 м)",
  "enum.range.Medium": "Средний (≤20 м)",
  "enum.range.Long": "Длинный (≤40 м)",

  "enum.creature_type.Aberration": "Аберрация",
  "enum.creature_type.Animal": "Животное",
  "enum.creature_type.Construct": "Конструкт",
  "enum.creature_type.Dragon": "Дракон",
  "enum.creature_type.Fey": "Фея",
  "enum.creature_type.Humanoid": "Гуманоид",
  "enum.creature_type.MagicalBeast": "Магический зверь",
  "enum.creature_type.MonstrousHumanoid": "Монстр-гуманоид",
  "enum.creature_type.Ooze": "Слизь",
  "enum.creature_type.Outsider": "Иноземец",
  "enum.creature_type.Plant": "Растение",
  "enum.creature_type.Swarm": "Рой",
  "enum.creature_type.Undead": "Нежить",
  "enum.creature_type.Vermin": "Тварь",
  "enum.creature_type.Incorporeal": "Бесплотный",

  "enum.alignment.Good": "Добрый",
  "enum.alignment.Evil": "Злой",
  "enum.alignment.Lawful": "Законопослушный",
  "enum.alignment.Chaotic": "Хаотичный",
  "enum.alignment.Neutral": "Нейтральный",

  "enum.condition.Paralyzed": "Парализован",
  "enum.condition.Stunned": "Оглушён",
  "enum.condition.Frightened": "Испуган",
  "enum.condition.Nauseated": "Тошнота",
  "enum.condition.Confused": "Смятение",
  "enum.condition.Blinded": "Ослеплён",
  "enum.condition.Prone": "Лежащий",
  "enum.condition.Entangled": "Опутан",
  "enum.condition.Exhausted": "Истощён",
  "enum.condition.Fatigued": "Утомлён",
  "enum.condition.Shaken": "Потрясён",
  "enum.condition.Sickened": "Болен",
  "enum.condition.Sleeping": "Спит",
  "enum.condition.Petrified": "Окаменел",
  "enum.condition.Slowed": "Замедлен",
  "enum.condition.Staggered": "Покачивается",
  "enum.condition.Dazed": "Ошеломлён",
  "enum.condition.Dazzled": "Ослеплён светом",
  "enum.condition.Helpless": "Беспомощен",
  "enum.condition.Cowering": "Скован страхом",
  "enum.condition.DeathDoor": "На пороге смерти",

  "cast.rod.label": "Жезл",
  "cast.rod.none": "(без жезла метамагии)",
  "enum.metamagic.Empower": "Empower",
  "enum.metamagic.Maximize": "Maximize",
  "enum.metamagic.Quicken": "Quicken",
  "enum.metamagic.Extend": "Extend",
  "enum.metamagic.Heighten": "Heighten",
  "enum.metamagic.Reach": "Reach",
  "enum.metamagic.Persistent": "Persistent",
  "enum.metamagic.Selective": "Selective",
  "enum.metamagic.Bolstered": "Bolstered",
  "enum.metamagic.CompletelyNormal": "Полностью обычное"
}
